mailrify/__init__.py
mailrify/__init__.pyi
mailrify/client.py
mailrify/config.py
mailrify/exceptions.py
mailrify/py.typed
mailrify/models/__init__.py
mailrify/models/_base.py
mailrify/resources/campaigns.py
mailrify/resources/contacts.py
mailrify/resources/domains.py
mailrify/resources/emails.py
mailrify/utils/pagination.py
mailrify/utils/serialization.py
mailrify-0.0.4.dist-info/METADATA
mailrify-0.0.4.dist-info/WHEEL
mailrify-0.0.4.dist-info/licenses/LICENSE
mailrify-0.0.4.dist-info/RECORD
