Metadata-Version: 2.4
Name: mailrify
Version: 0.0.4
Summary: Official Python SDK for Mailrify
Project-URL: Homepage, https://github.com/Mailrify/mailrify-python
Project-URL: Repository, https://github.com/Mailrify/mailrify-python
Project-URL: Issues, https://github.com/Mailrify/mailrify-python/issues
Project-URL: Changelog, https://github.com/Mailrify/mailrify-python/blob/main/CHANGELOG.md
Author-email: Mailrify <support@mailrify.com>
License: MIT
License-File: LICENSE
Keywords: api,email,mailrify,sdk
Classifier: Development Status :: 2 - Pre-Alpha
Classifier: Intended Audience :: Developers
Classifier: License :: OSI Approved :: MIT License
Classifier: Programming Language :: Python
Classifier: Programming Language :: Python :: 3
Classifier: Programming Language :: Python :: 3.9
Classifier: Programming Language :: Python :: 3.10
Classifier: Programming Language :: Python :: 3.11
Classifier: Programming Language :: Python :: 3.12
Classifier: Topic :: Communications :: Email
Classifier: Typing :: Typed
Requires-Python: >=3.9
Requires-Dist: httpx<1.0,>=0.25
Requires-Dist: pydantic<3,>=2
Requires-Dist: typing-extensions>=4.7
Provides-Extra: dev
Requires-Dist: black>=23.0; extra == 'dev'
Requires-Dist: build>=1.0; extra == 'dev'
Requires-Dist: coverage[toml]>=7.0; extra == 'dev'
Requires-Dist: mypy>=1.6; extra == 'dev'
Requires-Dist: pip-audit>=2.7; extra == 'dev'
Requires-Dist: pytest-asyncio>=0.21; extra == 'dev'
Requires-Dist: pytest-cov>=4.1; extra == 'dev'
Requires-Dist: pytest>=7.0; extra == 'dev'
Requires-Dist: respx>=0.20; extra == 'dev'
Requires-Dist: ruff>=0.1.5; extra == 'dev'
Requires-Dist: twine>=4.0; extra == 'dev'
